{"jsonrpc": "2.0", "id": "080a6102-5809-485a-abf7-9c39cb02111c", "result": {"New": {"Cold": {"Total": 0, "WhereReported": {}}, "Manual": {"Total": 0, "WhereReported": {}}, "Planned": {"Total": 0, "WhereReported": {}}}, "Lost": {"Cold": {"Total": 416, "WhereReported": {"UNKNOWN": 2, "ASANA": 15, "BREEZE": 3, "COLLAB": 1, "GCALENDAR": 13, "GITHUB": 16, "GITLAB": 1, "INSIGHTLY": 4, "JIRA": 1, "LIQUIDPLANNER": 1, "MSTODO": 22, "ODOO": 78, "OUTLOOK": 4, "PIVOTAL": 2, "REDMINE": 186, "TEAMWORK": 4, "TGTRACKER": 35, "TODOIST": 2, "TRELLO": 13, "VSTS": 1, "WRIKE": 2, "WUNDERLIST": 1, "YOUTRACK": 6, "ZOHO": 3}}, "Manual": {"Total": 3421, "WhereReported": {"UNKNOWN": 41, "ASANA": 180, "BASECAMP": 21, "BCV2": 7, "BITBUCKET": 5, "BREEZE": 26, "COLLAB": 41, "GCALENDAR": 55, "GITHUB": 165, "GITLAB": 19, "INSIGHTLY": 41, "JIRA": 23, "LIQUIDPLANNER": 13, "MANTIS": 35, "MSTODO": 12, "ODOO": 849, "OUTLOOK": 7, "PIVOTAL": 5, "PODIO": 3, "RALLY": 20, "REDBOOTH": 4, "REDMINE": 1283, "TEAMWORK": 27, "TGTRACKER": 332, "TODOIST": 7, "TRELLO": 73, "VSTS": 9, "WRIKE": 48, "WUNDERLIST": 17, "YOUTRACK": 24, "ZOHO": 29}}, "Planned": {"Total": 9326, "WhereReported": {"UNKNOWN": 111, "ASANA": 511, "BASECAMP": 16, "BCV2": 12, "BITBUCKET": 10, "BREEZE": 97, "COLLAB": 134, "GCALENDAR": 153, "GITHUB": 172, "GITLAB": 182, "INSIGHTLY": 186, "JIRA": 43, "LIQUIDPLANNER": 18, "MANTIS": 58, "MSTODO": 8, "ODOO": 2089, "OUTLOOK": 17, "PIVOTAL": 13, "PODIO": 9, "RALLY": 18, "REDBOOTH": 6, "REDMINE": 4204, "TEAMWORK": 68, "TGTRACKER": 694, "TODOIST": 20, "TRELLO": 151, "VSTS": 15, "WRIKE": 115, "WUNDERLIST": 45, "YOUTRACK": 57, "ZOHO": 94}}}, "Dedicated": {"Cold": {"Total": 303, "WhereReported": {"ASANA": 20, "BREEZE": 1, "COLLAB": 1, "GCALENDAR": 1, "GITLAB": 2, "ODOO": 111, "OUTLOOK": 1, "PODIO": 2, "REDBOOTH": 3, "REDMINE": 48, "TGTRACKER": 90, "TODOIST": 1, "TRELLO": 4, "VSTS": 17, "WUNDERLIST": 1}}, "Manual": {"Total": 1236, "WhereReported": {"UNKNOWN": 8, "ASANA": 75, "BASECAMP": 5, "BCV2": 8, "BREEZE": 9, "COLLAB": 8, "GCALENDAR": 17, "GITHUB": 15, "GITLAB": 7, "INSIGHTLY": 9, "JIRA": 2, "MANTIS": 3, "ODOO": 496, "OUTLOOK": 12, "PIVOTAL": 1, "PODIO": 1, "RALLY": 3, "REDBOOTH": 5, "REDMINE": 330, "TEAMWORK": 1, "TGTRACKER": 149, "TODOIST": 12, "TRELLO": 22, "VSTS": 13, "WRIKE": 3, "WUNDERLIST": 6, "YOUTRACK": 10, "ZOHO": 6}}, "Planned": {"Total": 2377, "WhereReported": {"UNKNOWN": 51, "ASANA": 99, "BASECAMP": 6, "BCV2": 4, "BITBUCKET": 18, "BREEZE": 23, "COLLAB": 48, "GCALENDAR": 62, "GITHUB": 49, "GITLAB": 31, "INSIGHTLY": 35, "JIRA": 11, "LIQUIDPLANNER": 24, "MANTIS": 24, "MSTODO": 6, "ODOO": 612, "OUTLOOK": 9, "PIVOTAL": 20, "PODIO": 19, "RALLY": 22, "REDBOOTH": 31, "REDMINE": 675, "TEAMWORK": 38, "TGTRACKER": 242, "TODOIST": 26, "TRELLO": 63, "VSTS": 28, "WRIKE": 37, "WUNDERLIST": 21, "YOUTRACK": 17, "ZOHO": 26}}}, "StableNew": {"Cold": {"Total": 0, "WhereReported": {}}, "Manual": {"Total": 2, "WhereReported": {"ASANA": 1, "ODOO": 1}}, "Planned": {"Total": 0, "WhereReported": {}}}, "StableLost": {"Cold": {"Total": 400, "WhereReported": {"UNKNOWN": 2, "ASANA": 13, "BREEZE": 3, "COLLAB": 1, "GCALENDAR": 13, "GITHUB": 15, "GITLAB": 1, "INSIGHTLY": 4, "JIRA": 1, "LIQUIDPLANNER": 1, "MSTODO": 22, "ODOO": 78, "OUTLOOK": 4, "PIVOTAL": 2, "REDMINE": 181, "TEAMWORK": 4, "TGTRACKER": 33, "TODOIST": 2, "TRELLO": 7, "VSTS": 1, "WRIKE": 2, "WUNDERLIST": 1, "YOUTRACK": 6, "ZOHO": 3}}, "Manual": {"Total": 2202, "WhereReported": {"UNKNOWN": 38, "ASANA": 132, "BASECAMP": 21, "BCV2": 7, "BITBUCKET": 5, "BREEZE": 26, "COLLAB": 41, "GCALENDAR": 55, "GITHUB": 158, "GITLAB": 18, "INSIGHTLY": 40, "JIRA": 23, "LIQUIDPLANNER": 13, "MANTIS": 27, "MSTODO": 12, "ODOO": 545, "OUTLOOK": 7, "PIVOTAL": 5, "PODIO": 3, "RALLY": 20, "REDBOOTH": 4, "REDMINE": 645, "TEAMWORK": 27, "TGTRACKER": 146, "TODOIST": 7, "TRELLO": 56, "VSTS": 9, "WRIKE": 47, "WUNDERLIST": 17, "YOUTRACK": 19, "ZOHO": 29}}, "Planned": {"Total": 7234, "WhereReported": {"UNKNOWN": 88, "ASANA": 350, "BASECAMP": 16, "BCV2": 11, "BITBUCKET": 10, "BREEZE": 92, "COLLAB": 129, "GCALENDAR": 149, "GITHUB": 124, "GITLAB": 123, "INSIGHTLY": 175, "JIRA": 41, "LIQUIDPLANNER": 18, "MANTIS": 56, "MSTODO": 8, "ODOO": 1613, "OUTLOOK": 17, "PIVOTAL": 13, "PODIO": 8, "RALLY": 18, "REDBOOTH": 6, "REDMINE": 3233, "TEAMWORK": 66, "TGTRACKER": 486, "TODOIST": 19, "TRELLO": 104, "VSTS": 15, "WRIKE": 79, "WUNDERLIST": 44, "YOUTRACK": 57, "ZOHO": 66}}}, "StableDedicated": {"Cold": {"Total": 311, "WhereReported": {"ASANA": 22, "BREEZE": 1, "COLLAB": 1, "GCALENDAR": 1, "GITHUB": 1, "GITLAB": 2, "ODOO": 109, "OUTLOOK": 1, "PODIO": 1, "REDBOOTH": 3, "REDMINE": 52, "TGTRACKER": 89, "TODOIST": 1, "TRELLO": 10, "VSTS": 16, "WUNDERLIST": 1}}, "Manual": {"Total": 2423, "WhereReported": {"UNKNOWN": 10, "ASANA": 122, "BASECAMP": 5, "BCV2": 8, "BREEZE": 9, "COLLAB": 8, "GCALENDAR": 17, "GITHUB": 22, "GITLAB": 8, "INSIGHTLY": 10, "MANTIS": 11, "ODOO": 797, "OUTLOOK": 12, "PIVOTAL": 1, "PODIO": 1, "RALLY": 3, "REDBOOTH": 5, "REDMINE": 968, "TEAMWORK": 1, "TGTRACKER": 310, "TODOIST": 12, "TRELLO": 39, "VSTS": 13, "WRIKE": 4, "WUNDERLIST": 6, "YOUTRACK": 15, "ZOHO": 6}}, "Planned": {"Total": 4429, "WhereReported": {"UNKNOWN": 74, "ASANA": 259, "BASECAMP": 6, "BCV2": 5, "BITBUCKET": 18, "BREEZE": 28, "COLLAB": 52, "GCALENDAR": 66, "GITHUB": 97, "GITLAB": 90, "INSIGHTLY": 46, "JIRA": 12, "LIQUIDPLANNER": 24, "MANTIS": 26, "MSTODO": 6, "ODOO": 1084, "OUTLOOK": 9, "PIVOTAL": 20, "PODIO": 20, "RALLY": 22, "REDBOOTH": 31, "REDMINE": 1643, "TEAMWORK": 40, "TGTRACKER": 422, "TODOIST": 27, "TRELLO": 110, "VSTS": 26, "WRIKE": 73, "WUNDERLIST": 22, "YOUTRACK": 17, "ZOHO": 54}}}}}
